ez_yaml/__init__.py
ez_yaml/settings.json
ez_yaml/__dependencies__/__init__.py
ez_yaml/__dependencies__/__sources__/ruamel/yaml/.hgignore
ez_yaml/__dependencies__/__sources__/ruamel/yaml/.hgtags
ez_yaml/__dependencies__/__sources__/ruamel/yaml/.readthedocs.yaml
ez_yaml/__dependencies__/__sources__/ruamel/yaml/CHANGES
ez_yaml/__dependencies__/__sources__/ruamel/yaml/LICENSE
ez_yaml/__dependencies__/__sources__/ruamel/yaml/MANIFEST.in
ez_yaml/__dependencies__/__sources__/ruamel/yaml/README.rst
ez_yaml/__dependencies__/__sources__/ruamel/yaml/__init__.py
ez_yaml/__dependencies__/__sources__/ruamel/yaml/anchor.py
ez_yaml/__dependencies__/__sources__/ruamel/yaml/comments.py
ez_yaml/__dependencies__/__sources__/ruamel/yaml/compat.py
ez_yaml/__dependencies__/__sources__/ruamel/yaml/composer.py
ez_yaml/__dependencies__/__sources__/ruamel/yaml/configobjwalker.py
ez_yaml/__dependencies__/__sources__/ruamel/yaml/constructor.py
ez_yaml/__dependencies__/__sources__/ruamel/yaml/cyaml.py
ez_yaml/__dependencies__/__sources__/ruamel/yaml/dumper.py
ez_yaml/__dependencies__/__sources__/ruamel/yaml/emitter.py
ez_yaml/__dependencies__/__sources__/ruamel/yaml/error.py
ez_yaml/__dependencies__/__sources__/ruamel/yaml/events.py
ez_yaml/__dependencies__/__sources__/ruamel/yaml/loader.py
ez_yaml/__dependencies__/__sources__/ruamel/yaml/main.py
ez_yaml/__dependencies__/__sources__/ruamel/yaml/nodes.py
ez_yaml/__dependencies__/__sources__/ruamel/yaml/parser.py
ez_yaml/__dependencies__/__sources__/ruamel/yaml/py.typed
ez_yaml/__dependencies__/__sources__/ruamel/yaml/reader.py
ez_yaml/__dependencies__/__sources__/ruamel/yaml/representer.py
ez_yaml/__dependencies__/__sources__/ruamel/yaml/resolver.py
ez_yaml/__dependencies__/__sources__/ruamel/yaml/scalarbool.py
ez_yaml/__dependencies__/__sources__/ruamel/yaml/scalarfloat.py
ez_yaml/__dependencies__/__sources__/ruamel/yaml/scalarint.py
ez_yaml/__dependencies__/__sources__/ruamel/yaml/scalarstring.py
ez_yaml-2.2.0.dist-info/METADATA
ez_yaml-2.2.0.dist-info/WHEEL
ez_yaml-2.2.0.dist-info/top_level.txt
ez_yaml-2.2.0.dist-info/RECORD
