Metadata-Version: 2.1
Name: ez-yaml
Version: 2.2.0
Summary: Straighforward wrapper around Ruamel Yaml
Home-page: https://github.com/jeff-hykin/ez_yaml
Author: Jeff Hykin
Author-email: jeff.hykin@gmail.com
License: MIT
Platform: UNKNOWN
Requires-Python: >=3.6
